spacy_annoy/__init__.py
spacy_annoy/pipeline.py
spacy_annoy-0.0.1.dist-info/LICENSE
spacy_annoy-0.0.1.dist-info/METADATA
spacy_annoy-0.0.1.dist-info/WHEEL
spacy_annoy-0.0.1.dist-info/top_level.txt
spacy_annoy-0.0.1.dist-info/RECORD
